{
    "greeting": 0,
    "goodbye": 1,
    "thanks": 2,
    "items": 3,
    "funny": 4,
    "form": 5,
    "reschedule": 6,
    "retrieve": 7,
    "edit": 8,
    "deadline": 9,
    "fee": 10,
    "authorized personnel": 11,
    "reapply": 12,
    "correcting": 13,
    "submit": 14,
    "claim": 15,
    "appointment": 16,
    "follow": 17,
    "address": 18,
    "format": 19,
    "mailing stamp": 20,
    "exceed": 21,
    "paste": 22,
    "ofw": 23,
    "4P's certificate": 24,
    "guardian": 25,
    "concerns": 26,
    "purpose": 27,
    "more than": 28,
    "less than": 29,
    "medical": 30,
    "requirements": 31,
    "satellite": 32,
    "form 138": 33,
    "CS": 34,
    "CSSP": 35,
    "BUTC": 36,
    "CE": 37,
    "BUGC": 38,
    "CAL": 39,
    "IDeA": 40,
    "CN": 41,
    "JMRIGD": 42,
    "IPESR": 43,
    "CBEM": 44,
    "CIT": 45,
    "CENG": 46,
    "BUCAF": 47,
    "BUPC": 48,
    "CDM": 49,
    "general requirements": 50,
    "submitting requirements": 51,
    "announcement": 52,
    "qualification": 53,
    "topics": 54,
    "date of release": 55,
    "test centers": 56,
    "mobile phone": 57
}